src/sanstylex_demo/__init__.py
sanstylex_demo-0.0.1.dist-info/LICENSE
sanstylex_demo-0.0.1.dist-info/WHEEL
sanstylex_demo-0.0.1.dist-info/METADATA
sanstylex_demo-0.0.1.dist-info/RECORD
