Metadata-Version: 2.1
Name: sanstylex-demo
Version: 0.0.1
Summary: Dive into Python.
Author-email: xinetzone <735613050@qq.com>
Maintainer-email: xinetzone <735613050@qq.com>
Requires-Python: >=3.10
Classifier: License :: OSI Approved :: Apache Software License
Requires-Dist: d2py
Requires-Dist: sphinx<6 ; extra == "doc"
Requires-Dist: sphinxcontrib-youtube ; extra == "doc"
Requires-Dist: sphinx-favicon ; extra == "doc"
Requires-Dist: xyzstyle ; extra == "doc"
Requires-Dist: pydata-sphinx-theme>=0.7.2 ; extra == "doc"
Requires-Dist: sphinx-book-theme ; extra == "doc"
Requires-Dist: ablog ; extra == "doc"
Requires-Dist: ipywidgets>=7.0.0 ; extra == "doc"
Requires-Dist: myst-nb ; extra == "doc"
Requires-Dist: sphinxcontrib-websupport ; extra == "doc"
Requires-Dist: sphinx-thebe ; extra == "doc"
Requires-Dist: sphinx-copybutton ; extra == "doc"
Requires-Dist: sphinx-comments ; extra == "doc"
Requires-Dist: plotly ; extra == "doc"
Requires-Dist: pandas ; extra == "doc"
Requires-Dist: matplotlib ; extra == "doc"
Requires-Dist: sphinxcontrib-mermaid ; extra == "doc"
Requires-Dist: sphinx-design ; extra == "doc"
Requires-Dist: sphinx-automodapi ; extra == "doc"
Requires-Dist: sphinxext-rediraffe ; extra == "doc"
Requires-Dist: sphinx-plotly-directive ; extra == "doc"
Requires-Dist: jupyter-dash ; extra == "doc"
Requires-Dist: plotly ; extra == "doc"
Requires-Dist: sphinx-sitemap ; extra == "doc"
Requires-Dist: bokeh ; extra == "doc"
Project-URL: Home, https://github.com/sanstylex/sanstylex-demo
Provides-Extra: doc
